{"name": "addiction", "threshold": 5.5, "maxAbsValue": 8.934185981750488, "maxClusterSize": 116, "diverging": false, "structures": {"lh_cortex": {"blocky": {"pos": 0, "idx": 1, "val": 2, "clu": 3, "nverts": 496, "ntris": 248}, "smooth": {"pos": 4, "idx": 5, "val": 6, "clu": 7, "nverts": 862, "ntris": 1720}}, "rh_cortex": {"blocky": {"pos": 8, "idx": 9, "val": 10, "clu": 11, "nverts": 504, "ntris": 252}, "smooth": {"pos": 12, "idx": 13, "val": 14, "clu": 15, "nverts": 768, "ntris": 1520}}, "subcort_l": {"blocky": {"pos": 16, "idx": 17, "val": 18, "clu": 19, "nverts": 640, "ntris": 320}, "smooth": {"pos": 20, "idx": 21, "val": 22, "clu": 23, "nverts": 2458, "ntris": 4912}}, "subcort_r": {"blocky": {"pos": 24, "idx": 25, "val": 26, "clu": 27, "nverts": 752, "ntris": 376}, "smooth": {"pos": 28, "idx": 29, "val": 30, "clu": 31, "nverts": 2628, "ntris": 5252}}, "brainstem": {"blocky": {"pos": 32, "idx": 33, "val": 34, "clu": 35, "nverts": 24, "ntris": 12}, "smooth": {"pos": 32, "idx": 33, "val": 34, "clu": 35, "nverts": 24, "ntris": 12}}}, "bufferLayout": [[0, 5952], [5952, 2976], [8928, 1984], [10912, 1984], [12896, 10344], [23240, 20640], [43880, 3448], [47328, 3448], [50776, 6048], [56824, 3024], [59848, 2016], [61864, 2016], [63880, 9216], [73096, 18240], [91336, 3072], [94408, 3072], [97480, 7680], [105160, 3840], [109000, 2560], [111560, 2560], [114120, 29496], [143616, 58944], [202560, 9832], [212392, 9832], [222224, 9024], [231248, 4512], [235760, 3008], [238768, 3008], [241776, 31536], [273312, 63024], [336336, 10512], [346848, 10512], [357360, 288], [357648, 144], [357792, 96], [357888, 96]], "buffersFile": "overlay_0.bin"}